pokemaster2/__init__.py
pokemaster2/cli.py
pokemaster2/db/__init__.py
pokemaster2/db/default.py
pokemaster2/db/io.py
pokemaster2/db/tables.py
pokemaster2/pokemon.py
pokemaster2/prng.py
pokemaster2-21.12.3.dist-info/entry_points.txt
pokemaster2-21.12.3.dist-info/LICENSE.rst
pokemaster2-21.12.3.dist-info/WHEEL
pokemaster2-21.12.3.dist-info/METADATA
pokemaster2-21.12.3.dist-info/RECORD
