Metadata-Version: 2.1
Name: pokemaster2
Version: 21.12.3
Summary: Get Real, Living™ Pokémon in Python
Home-page: https://github.com/kipyin/pokemaster2
Keywords: pokemaster2,pokemon,pokedex,pokemaster
Author: Kip Yin
Author-email: 28321392+kipyin@users.noreply.github.com
Requires-Python: >=3.8,<3.11
Classifier: Development Status :: 2 - Pre-Alpha
Classifier: Intended Audience :: Developers
Classifier: License :: OSI Approved :: MIT License
Classifier: Natural Language :: English
Classifier: Programming Language :: Python :: 3
Classifier: Programming Language :: Python :: 3.10
Classifier: Programming Language :: Python :: 3.7
Classifier: Programming Language :: Python :: 3.8
Classifier: Programming Language :: Python :: 3.9
Requires-Dist: attrs (>=21.2.0,<22.0.0)
Requires-Dist: click (>=8.0.3,<9.0.0)
Requires-Dist: importlib-resources (>=5.4.0,<6.0.0)
Requires-Dist: loguru (>=0.5.3,<0.6.0)
Requires-Dist: peewee (>=3.14.8,<4.0.0)
Project-URL: Bug Tracker, https://github.com/kipyin/pokemaster2/issues
Project-URL: Documentation, https://pokemaster2.readthedocs.io
Project-URL: Repository, https://github.com/kipyin/pokemaster2
